__init__.py
minibone/__init__.py
minibone/async_daemon.py
minibone/config.py
minibone/daemon.py
minibone/emailer.py
minibone/html_base.py
minibone/httpt.py
minibone/io_threads.py
minibone/logging_utils.py
minibone/processes.py
minibone/storing.py
minibone-0.9.1.dist-info/licenses/LICENSE
minibone-0.9.1.dist-info/METADATA
minibone-0.9.1.dist-info/WHEEL
minibone-0.9.1.dist-info/top_level.txt
minibone-0.9.1.dist-info/RECORD
