Metadata-Version: 2.4
Name: minibone
Version: 0.9.1
Summary: Small boilerplate with tools for concurrent/parallel processing.
Author-email: Erick Romero <erick@gjrlabs.com>
Project-URL: Homepage, https://github.com/erromu/minibone/
Project-URL: Bug Tracker, https://github.com/erromu/minibone/issues
Project-URL: Issues, https://github.com/erromu/minibone/issues
Project-URL: Documentation, https://www.gjrlabs.com
Project-URL: Repository, https://github.com/erromu/minibone.git
Keywords: multithreading,asyncio,task,job,background,concurrent,parallel
Classifier: Development Status :: 5 - Production/Stable
Classifier: Intended Audience :: Developers
Classifier: Operating System :: OS Independent
Classifier: Programming Language :: Python :: 3.10
Classifier: Topic :: Utilities
Classifier: Topic :: Software Development :: Libraries
Requires-Python: >=3.10
License-File: LICENSE
Requires-Dist: aiofiles
Requires-Dist: pyyaml
Requires-Dist: httpx
Requires-Dist: tomlkit
Dynamic: license-file
